plotestrem/__init__.py
plotestrem/utils.py
plotestrem-0.0.2.dist-info/LICENSE
plotestrem-0.0.2.dist-info/METADATA
plotestrem-0.0.2.dist-info/WHEEL
plotestrem-0.0.2.dist-info/top_level.txt
plotestrem-0.0.2.dist-info/RECORD
