Metadata-Version: 2.1
Name: plotestrem
Version: 0.0.2
Summary: A simple Python script to plot and fit data (similar to Origin or SciDavis), but free, open source and LaTeX-friendly.
Home-page: https://github.com/hellmrf/plotestrem
Author: Heliton Martins Reis Filho
Author-email: helitonmrf@gmail.com
License: GPL-v3.0
Platform: UNKNOWN
Classifier: Programming Language :: Python :: 3
Classifier: Operating System :: OS Independent
Requires-Python: >=3.6
License-File: LICENSE
Requires-Dist: numpy
Requires-Dist: scipy
Requires-Dist: matplotlib
